{
  "generatedAt": "2026-06-22T04:46:13.240Z",
  "educationOnly": true,
  "productionReady": false,
  "learnerFacingRelease": false,
  "approvalStatus": "not_approved",
  "mergePreviewStatus": "packet_014_merge_preview_blocked_missing_ready_packet_input",
  "mergePreviewMode": "dry_run_packet_input_copy_to_full_source_fit_draft_mapping",
  "packetId": "node-public-source-fit-batch-014-packet",
  "batchId": "node-public-source-fit-batch-014",
  "module": "风险管理",
  "packetInputPath": "docs/reviewer-inputs/KNOWLEDGE_NODE_PUBLIC_SOURCE_FIT_REVIEW_PACKET_014_INPUT_COPY_TEMPLATE.json",
  "packetValidationPath": "docs/KNOWLEDGE_NODE_PUBLIC_SOURCE_FIT_REVIEW_PACKET_014_INPUT_COPY_TEMPLATE_VALIDATION.json",
  "fullDraftInputPath": "docs/reviewer-inputs/KNOWLEDGE_NODE_PUBLIC_SOURCE_FIT_REVIEW_INPUT_DRAFT.json",
  "fullValidationPath": "docs/KNOWLEDGE_NODE_PUBLIC_SOURCE_FIT_REVIEW_INPUT_VALIDATION.json",
  "packetRows": 60,
  "fullDraftRows": 1638,
  "fullValidationRows": 1638,
  "mappedRows": 60,
  "missingTargetRows": 0,
  "readyRows": 0,
  "blockedRows": 60,
  "packetValidationStatus": "blocked_missing_real_reviewer_source_fit_input",
  "packetReadyRows": 0,
  "packetBlockedRows": 60,
  "packetMissingFieldRows": 60,
  "packetForbiddenHitRows": 0,
  "packetRealHumanInputEntries": 0,
  "fullDraftReadyRowsBeforeMerge": 0,
  "fullDraftBlockedRowsBeforeMerge": 1638,
  "mergeAllowedNow": false,
  "writeAllowedNow": false,
  "manualAuthorizationRequired": true,
  "mergeRows": [
    {
      "packetRowIndex": 0,
      "targetFullDraftRowIndex": 846,
      "reviewId": "knv2_0227::corpus_0423",
      "nodeId": "knv2_0227",
      "documentId": "corpus_0423",
      "sourceName": "Wikipedia: Diversification (finance)",
      "mappedToFullDraft": true,
      "packetValidationStatus": "blocked_missing_or_invalid_reviewer_input",
      "readyForMerge": false,
      "mergeBlockedReason": "packet_row_not_ready_for_merge",
      "fieldCopyPlan": {
        "reviewerDecision": {
          "from": "/rows/0/reviewerDecision",
          "to": "/rows/846/reviewerDecision"
        },
        "sourceFitNotes": {
          "from": "/rows/0/sourceFitNotes",
          "to": "/rows/846/sourceFitNotes"
        },
        "citationUse": {
          "from": "/rows/0/citationUse",
          "to": "/rows/846/citationUse"
        },
        "reviewerName": {
          "from": "/rows/0/reviewerName",
          "to": "/rows/846/reviewerName"
        },
        "reviewedAt": {
          "from": "/rows/0/reviewedAt",
          "to": "/rows/846/reviewedAt"
        },
        "realHumanInput": {
          "from": "/rows/0/realHumanInput",
          "to": "/rows/846/realHumanInput"
        }
      }
    },
    {
      "packetRowIndex": 1,
      "targetFullDraftRowIndex": 847,
      "reviewId": "knv2_0227::corpus_0042",
      "nodeId": "knv2_0227",
      "documentId": "corpus_0042",
      "sourceName": "CFTC Speculative Limits",
      "mappedToFullDraft": true,
      "packetValidationStatus": "blocked_missing_or_invalid_reviewer_input",
      "readyForMerge": false,
      "mergeBlockedReason": "packet_row_not_ready_for_merge",
      "fieldCopyPlan": {
        "reviewerDecision": {
          "from": "/rows/1/reviewerDecision",
          "to": "/rows/847/reviewerDecision"
        },
        "sourceFitNotes": {
          "from": "/rows/1/sourceFitNotes",
          "to": "/rows/847/sourceFitNotes"
        },
        "citationUse": {
          "from": "/rows/1/citationUse",
          "to": "/rows/847/citationUse"
        },
        "reviewerName": {
          "from": "/rows/1/reviewerName",
          "to": "/rows/847/reviewerName"
        },
        "reviewedAt": {
          "from": "/rows/1/reviewedAt",
          "to": "/rows/847/reviewedAt"
        },
        "realHumanInput": {
          "from": "/rows/1/realHumanInput",
          "to": "/rows/847/realHumanInput"
        }
      }
    },
    {
      "packetRowIndex": 2,
      "targetFullDraftRowIndex": 848,
      "reviewId": "knv2_0227::corpus_0646",
      "nodeId": "knv2_0227",
      "documentId": "corpus_0646",
      "sourceName": "A note on estimating stochastic volatility and its volatility: a new simple method",
      "mappedToFullDraft": true,
      "packetValidationStatus": "blocked_missing_or_invalid_reviewer_input",
      "readyForMerge": false,
      "mergeBlockedReason": "packet_row_not_ready_for_merge",
      "fieldCopyPlan": {
        "reviewerDecision": {
          "from": "/rows/2/reviewerDecision",
          "to": "/rows/848/reviewerDecision"
        },
        "sourceFitNotes": {
          "from": "/rows/2/sourceFitNotes",
          "to": "/rows/848/sourceFitNotes"
        },
        "citationUse": {
          "from": "/rows/2/citationUse",
          "to": "/rows/848/citationUse"
        },
        "reviewerName": {
          "from": "/rows/2/reviewerName",
          "to": "/rows/848/reviewerName"
        },
        "reviewedAt": {
          "from": "/rows/2/reviewedAt",
          "to": "/rows/848/reviewedAt"
        },
        "realHumanInput": {
          "from": "/rows/2/realHumanInput",
          "to": "/rows/848/realHumanInput"
        }
      }
    },
    {
      "packetRowIndex": 3,
      "targetFullDraftRowIndex": 849,
      "reviewId": "knv2_0227::corpus_0422",
      "nodeId": "knv2_0227",
      "documentId": "corpus_0422",
      "sourceName": "Wikipedia: Drawdown (economics)",
      "mappedToFullDraft": true,
      "packetValidationStatus": "blocked_missing_or_invalid_reviewer_input",
      "readyForMerge": false,
      "mergeBlockedReason": "packet_row_not_ready_for_merge",
      "fieldCopyPlan": {
        "reviewerDecision": {
          "from": "/rows/3/reviewerDecision",
          "to": "/rows/849/reviewerDecision"
        },
        "sourceFitNotes": {
          "from": "/rows/3/sourceFitNotes",
          "to": "/rows/849/sourceFitNotes"
        },
        "citationUse": {
          "from": "/rows/3/citationUse",
          "to": "/rows/849/citationUse"
        },
        "reviewerName": {
          "from": "/rows/3/reviewerName",
          "to": "/rows/849/reviewerName"
        },
        "reviewedAt": {
          "from": "/rows/3/reviewedAt",
          "to": "/rows/849/reviewedAt"
        },
        "realHumanInput": {
          "from": "/rows/3/realHumanInput",
          "to": "/rows/849/realHumanInput"
        }
      }
    },
    {
      "packetRowIndex": 4,
      "targetFullDraftRowIndex": 850,
      "reviewId": "knv2_0227::corpus_0421",
      "nodeId": "knv2_0227",
      "documentId": "corpus_0421",
      "sourceName": "Wikipedia: Kelly criterion",
      "mappedToFullDraft": true,
      "packetValidationStatus": "blocked_missing_or_invalid_reviewer_input",
      "readyForMerge": false,
      "mergeBlockedReason": "packet_row_not_ready_for_merge",
      "fieldCopyPlan": {
        "reviewerDecision": {
          "from": "/rows/4/reviewerDecision",
          "to": "/rows/850/reviewerDecision"
        },
        "sourceFitNotes": {
          "from": "/rows/4/sourceFitNotes",
          "to": "/rows/850/sourceFitNotes"
        },
        "citationUse": {
          "from": "/rows/4/citationUse",
          "to": "/rows/850/citationUse"
        },
        "reviewerName": {
          "from": "/rows/4/reviewerName",
          "to": "/rows/850/reviewerName"
        },
        "reviewedAt": {
          "from": "/rows/4/reviewedAt",
          "to": "/rows/850/reviewedAt"
        },
        "realHumanInput": {
          "from": "/rows/4/realHumanInput",
          "to": "/rows/850/realHumanInput"
        }
      }
    },
    {
      "packetRowIndex": 5,
      "targetFullDraftRowIndex": 851,
      "reviewId": "knv2_0227::corpus_0458",
      "nodeId": "knv2_0227",
      "documentId": "corpus_0458",
      "sourceName": "Wikipedia: Leverage (finance)",
      "mappedToFullDraft": true,
      "packetValidationStatus": "blocked_missing_or_invalid_reviewer_input",
      "readyForMerge": false,
      "mergeBlockedReason": "packet_row_not_ready_for_merge",
      "fieldCopyPlan": {
        "reviewerDecision": {
          "from": "/rows/5/reviewerDecision",
          "to": "/rows/851/reviewerDecision"
        },
        "sourceFitNotes": {
          "from": "/rows/5/sourceFitNotes",
          "to": "/rows/851/sourceFitNotes"
        },
        "citationUse": {
          "from": "/rows/5/citationUse",
          "to": "/rows/851/citationUse"
        },
        "reviewerName": {
          "from": "/rows/5/reviewerName",
          "to": "/rows/851/reviewerName"
        },
        "reviewedAt": {
          "from": "/rows/5/reviewedAt",
          "to": "/rows/851/reviewedAt"
        },
        "realHumanInput": {
          "from": "/rows/5/realHumanInput",
          "to": "/rows/851/realHumanInput"
        }
      }
    },
    {
      "packetRowIndex": 6,
      "targetFullDraftRowIndex": 918,
      "reviewId": "knv2_0239::corpus_0423",
      "nodeId": "knv2_0239",
      "documentId": "corpus_0423",
      "sourceName": "Wikipedia: Diversification (finance)",
      "mappedToFullDraft": true,
      "packetValidationStatus": "blocked_missing_or_invalid_reviewer_input",
      "readyForMerge": false,
      "mergeBlockedReason": "packet_row_not_ready_for_merge",
      "fieldCopyPlan": {
        "reviewerDecision": {
          "from": "/rows/6/reviewerDecision",
          "to": "/rows/918/reviewerDecision"
        },
        "sourceFitNotes": {
          "from": "/rows/6/sourceFitNotes",
          "to": "/rows/918/sourceFitNotes"
        },
        "citationUse": {
          "from": "/rows/6/citationUse",
          "to": "/rows/918/citationUse"
        },
        "reviewerName": {
          "from": "/rows/6/reviewerName",
          "to": "/rows/918/reviewerName"
        },
        "reviewedAt": {
          "from": "/rows/6/reviewedAt",
          "to": "/rows/918/reviewedAt"
        },
        "realHumanInput": {
          "from": "/rows/6/realHumanInput",
          "to": "/rows/918/realHumanInput"
        }
      }
    },
    {
      "packetRowIndex": 7,
      "targetFullDraftRowIndex": 919,
      "reviewId": "knv2_0239::corpus_0042",
      "nodeId": "knv2_0239",
      "documentId": "corpus_0042",
      "sourceName": "CFTC Speculative Limits",
      "mappedToFullDraft": true,
      "packetValidationStatus": "blocked_missing_or_invalid_reviewer_input",
      "readyForMerge": false,
      "mergeBlockedReason": "packet_row_not_ready_for_merge",
      "fieldCopyPlan": {
        "reviewerDecision": {
          "from": "/rows/7/reviewerDecision",
          "to": "/rows/919/reviewerDecision"
        },
        "sourceFitNotes": {
          "from": "/rows/7/sourceFitNotes",
          "to": "/rows/919/sourceFitNotes"
        },
        "citationUse": {
          "from": "/rows/7/citationUse",
          "to": "/rows/919/citationUse"
        },
        "reviewerName": {
          "from": "/rows/7/reviewerName",
          "to": "/rows/919/reviewerName"
        },
        "reviewedAt": {
          "from": "/rows/7/reviewedAt",
          "to": "/rows/919/reviewedAt"
        },
        "realHumanInput": {
          "from": "/rows/7/realHumanInput",
          "to": "/rows/919/realHumanInput"
        }
      }
    },
    {
      "packetRowIndex": 8,
      "targetFullDraftRowIndex": 920,
      "reviewId": "knv2_0239::corpus_0646",
      "nodeId": "knv2_0239",
      "documentId": "corpus_0646",
      "sourceName": "A note on estimating stochastic volatility and its volatility: a new simple method",
      "mappedToFullDraft": true,
      "packetValidationStatus": "blocked_missing_or_invalid_reviewer_input",
      "readyForMerge": false,
      "mergeBlockedReason": "packet_row_not_ready_for_merge",
      "fieldCopyPlan": {
        "reviewerDecision": {
          "from": "/rows/8/reviewerDecision",
          "to": "/rows/920/reviewerDecision"
        },
        "sourceFitNotes": {
          "from": "/rows/8/sourceFitNotes",
          "to": "/rows/920/sourceFitNotes"
        },
        "citationUse": {
          "from": "/rows/8/citationUse",
          "to": "/rows/920/citationUse"
        },
        "reviewerName": {
          "from": "/rows/8/reviewerName",
          "to": "/rows/920/reviewerName"
        },
        "reviewedAt": {
          "from": "/rows/8/reviewedAt",
          "to": "/rows/920/reviewedAt"
        },
        "realHumanInput": {
          "from": "/rows/8/realHumanInput",
          "to": "/rows/920/realHumanInput"
        }
      }
    },
    {
      "packetRowIndex": 9,
      "targetFullDraftRowIndex": 921,
      "reviewId": "knv2_0239::corpus_0422",
      "nodeId": "knv2_0239",
      "documentId": "corpus_0422",
      "sourceName": "Wikipedia: Drawdown (economics)",
      "mappedToFullDraft": true,
      "packetValidationStatus": "blocked_missing_or_invalid_reviewer_input",
      "readyForMerge": false,
      "mergeBlockedReason": "packet_row_not_ready_for_merge",
      "fieldCopyPlan": {
        "reviewerDecision": {
          "from": "/rows/9/reviewerDecision",
          "to": "/rows/921/reviewerDecision"
        },
        "sourceFitNotes": {
          "from": "/rows/9/sourceFitNotes",
          "to": "/rows/921/sourceFitNotes"
        },
        "citationUse": {
          "from": "/rows/9/citationUse",
          "to": "/rows/921/citationUse"
        },
        "reviewerName": {
          "from": "/rows/9/reviewerName",
          "to": "/rows/921/reviewerName"
        },
        "reviewedAt": {
          "from": "/rows/9/reviewedAt",
          "to": "/rows/921/reviewedAt"
        },
        "realHumanInput": {
          "from": "/rows/9/realHumanInput",
          "to": "/rows/921/realHumanInput"
        }
      }
    },
    {
      "packetRowIndex": 10,
      "targetFullDraftRowIndex": 922,
      "reviewId": "knv2_0239::corpus_0421",
      "nodeId": "knv2_0239",
      "documentId": "corpus_0421",
      "sourceName": "Wikipedia: Kelly criterion",
      "mappedToFullDraft": true,
      "packetValidationStatus": "blocked_missing_or_invalid_reviewer_input",
      "readyForMerge": false,
      "mergeBlockedReason": "packet_row_not_ready_for_merge",
      "fieldCopyPlan": {
        "reviewerDecision": {
          "from": "/rows/10/reviewerDecision",
          "to": "/rows/922/reviewerDecision"
        },
        "sourceFitNotes": {
          "from": "/rows/10/sourceFitNotes",
          "to": "/rows/922/sourceFitNotes"
        },
        "citationUse": {
          "from": "/rows/10/citationUse",
          "to": "/rows/922/citationUse"
        },
        "reviewerName": {
          "from": "/rows/10/reviewerName",
          "to": "/rows/922/reviewerName"
        },
        "reviewedAt": {
          "from": "/rows/10/reviewedAt",
          "to": "/rows/922/reviewedAt"
        },
        "realHumanInput": {
          "from": "/rows/10/realHumanInput",
          "to": "/rows/922/realHumanInput"
        }
      }
    },
    {
      "packetRowIndex": 11,
      "targetFullDraftRowIndex": 923,
      "reviewId": "knv2_0239::corpus_0458",
      "nodeId": "knv2_0239",
      "documentId": "corpus_0458",
      "sourceName": "Wikipedia: Leverage (finance)",
      "mappedToFullDraft": true,
      "packetValidationStatus": "blocked_missing_or_invalid_reviewer_input",
      "readyForMerge": false,
      "mergeBlockedReason": "packet_row_not_ready_for_merge",
      "fieldCopyPlan": {
        "reviewerDecision": {
          "from": "/rows/11/reviewerDecision",
          "to": "/rows/923/reviewerDecision"
        },
        "sourceFitNotes": {
          "from": "/rows/11/sourceFitNotes",
          "to": "/rows/923/sourceFitNotes"
        },
        "citationUse": {
          "from": "/rows/11/citationUse",
          "to": "/rows/923/citationUse"
        },
        "reviewerName": {
          "from": "/rows/11/reviewerName",
          "to": "/rows/923/reviewerName"
        },
        "reviewedAt": {
          "from": "/rows/11/reviewedAt",
          "to": "/rows/923/reviewedAt"
        },
        "realHumanInput": {
          "from": "/rows/11/realHumanInput",
          "to": "/rows/923/realHumanInput"
        }
      }
    },
    {
      "packetRowIndex": 12,
      "targetFullDraftRowIndex": 984,
      "reviewId": "knv2_0251::corpus_0423",
      "nodeId": "knv2_0251",
      "documentId": "corpus_0423",
      "sourceName": "Wikipedia: Diversification (finance)",
      "mappedToFullDraft": true,
      "packetValidationStatus": "blocked_missing_or_invalid_reviewer_input",
      "readyForMerge": false,
      "mergeBlockedReason": "packet_row_not_ready_for_merge",
      "fieldCopyPlan": {
        "reviewerDecision": {
          "from": "/rows/12/reviewerDecision",
          "to": "/rows/984/reviewerDecision"
        },
        "sourceFitNotes": {
          "from": "/rows/12/sourceFitNotes",
          "to": "/rows/984/sourceFitNotes"
        },
        "citationUse": {
          "from": "/rows/12/citationUse",
          "to": "/rows/984/citationUse"
        },
        "reviewerName": {
          "from": "/rows/12/reviewerName",
          "to": "/rows/984/reviewerName"
        },
        "reviewedAt": {
          "from": "/rows/12/reviewedAt",
          "to": "/rows/984/reviewedAt"
        },
        "realHumanInput": {
          "from": "/rows/12/realHumanInput",
          "to": "/rows/984/realHumanInput"
        }
      }
    },
    {
      "packetRowIndex": 13,
      "targetFullDraftRowIndex": 985,
      "reviewId": "knv2_0251::corpus_0042",
      "nodeId": "knv2_0251",
      "documentId": "corpus_0042",
      "sourceName": "CFTC Speculative Limits",
      "mappedToFullDraft": true,
      "packetValidationStatus": "blocked_missing_or_invalid_reviewer_input",
      "readyForMerge": false,
      "mergeBlockedReason": "packet_row_not_ready_for_merge",
      "fieldCopyPlan": {
        "reviewerDecision": {
          "from": "/rows/13/reviewerDecision",
          "to": "/rows/985/reviewerDecision"
        },
        "sourceFitNotes": {
          "from": "/rows/13/sourceFitNotes",
          "to": "/rows/985/sourceFitNotes"
        },
        "citationUse": {
          "from": "/rows/13/citationUse",
          "to": "/rows/985/citationUse"
        },
        "reviewerName": {
          "from": "/rows/13/reviewerName",
          "to": "/rows/985/reviewerName"
        },
        "reviewedAt": {
          "from": "/rows/13/reviewedAt",
          "to": "/rows/985/reviewedAt"
        },
        "realHumanInput": {
          "from": "/rows/13/realHumanInput",
          "to": "/rows/985/realHumanInput"
        }
      }
    },
    {
      "packetRowIndex": 14,
      "targetFullDraftRowIndex": 986,
      "reviewId": "knv2_0251::corpus_0646",
      "nodeId": "knv2_0251",
      "documentId": "corpus_0646",
      "sourceName": "A note on estimating stochastic volatility and its volatility: a new simple method",
      "mappedToFullDraft": true,
      "packetValidationStatus": "blocked_missing_or_invalid_reviewer_input",
      "readyForMerge": false,
      "mergeBlockedReason": "packet_row_not_ready_for_merge",
      "fieldCopyPlan": {
        "reviewerDecision": {
          "from": "/rows/14/reviewerDecision",
          "to": "/rows/986/reviewerDecision"
        },
        "sourceFitNotes": {
          "from": "/rows/14/sourceFitNotes",
          "to": "/rows/986/sourceFitNotes"
        },
        "citationUse": {
          "from": "/rows/14/citationUse",
          "to": "/rows/986/citationUse"
        },
        "reviewerName": {
          "from": "/rows/14/reviewerName",
          "to": "/rows/986/reviewerName"
        },
        "reviewedAt": {
          "from": "/rows/14/reviewedAt",
          "to": "/rows/986/reviewedAt"
        },
        "realHumanInput": {
          "from": "/rows/14/realHumanInput",
          "to": "/rows/986/realHumanInput"
        }
      }
    },
    {
      "packetRowIndex": 15,
      "targetFullDraftRowIndex": 987,
      "reviewId": "knv2_0251::corpus_0422",
      "nodeId": "knv2_0251",
      "documentId": "corpus_0422",
      "sourceName": "Wikipedia: Drawdown (economics)",
      "mappedToFullDraft": true,
      "packetValidationStatus": "blocked_missing_or_invalid_reviewer_input",
      "readyForMerge": false,
      "mergeBlockedReason": "packet_row_not_ready_for_merge",
      "fieldCopyPlan": {
        "reviewerDecision": {
          "from": "/rows/15/reviewerDecision",
          "to": "/rows/987/reviewerDecision"
        },
        "sourceFitNotes": {
          "from": "/rows/15/sourceFitNotes",
          "to": "/rows/987/sourceFitNotes"
        },
        "citationUse": {
          "from": "/rows/15/citationUse",
          "to": "/rows/987/citationUse"
        },
        "reviewerName": {
          "from": "/rows/15/reviewerName",
          "to": "/rows/987/reviewerName"
        },
        "reviewedAt": {
          "from": "/rows/15/reviewedAt",
          "to": "/rows/987/reviewedAt"
        },
        "realHumanInput": {
          "from": "/rows/15/realHumanInput",
          "to": "/rows/987/realHumanInput"
        }
      }
    },
    {
      "packetRowIndex": 16,
      "targetFullDraftRowIndex": 988,
      "reviewId": "knv2_0251::corpus_0421",
      "nodeId": "knv2_0251",
      "documentId": "corpus_0421",
      "sourceName": "Wikipedia: Kelly criterion",
      "mappedToFullDraft": true,
      "packetValidationStatus": "blocked_missing_or_invalid_reviewer_input",
      "readyForMerge": false,
      "mergeBlockedReason": "packet_row_not_ready_for_merge",
      "fieldCopyPlan": {
        "reviewerDecision": {
          "from": "/rows/16/reviewerDecision",
          "to": "/rows/988/reviewerDecision"
        },
        "sourceFitNotes": {
          "from": "/rows/16/sourceFitNotes",
          "to": "/rows/988/sourceFitNotes"
        },
        "citationUse": {
          "from": "/rows/16/citationUse",
          "to": "/rows/988/citationUse"
        },
        "reviewerName": {
          "from": "/rows/16/reviewerName",
          "to": "/rows/988/reviewerName"
        },
        "reviewedAt": {
          "from": "/rows/16/reviewedAt",
          "to": "/rows/988/reviewedAt"
        },
        "realHumanInput": {
          "from": "/rows/16/realHumanInput",
          "to": "/rows/988/realHumanInput"
        }
      }
    },
    {
      "packetRowIndex": 17,
      "targetFullDraftRowIndex": 989,
      "reviewId": "knv2_0251::corpus_0458",
      "nodeId": "knv2_0251",
      "documentId": "corpus_0458",
      "sourceName": "Wikipedia: Leverage (finance)",
      "mappedToFullDraft": true,
      "packetValidationStatus": "blocked_missing_or_invalid_reviewer_input",
      "readyForMerge": false,
      "mergeBlockedReason": "packet_row_not_ready_for_merge",
      "fieldCopyPlan": {
        "reviewerDecision": {
          "from": "/rows/17/reviewerDecision",
          "to": "/rows/989/reviewerDecision"
        },
        "sourceFitNotes": {
          "from": "/rows/17/sourceFitNotes",
          "to": "/rows/989/sourceFitNotes"
        },
        "citationUse": {
          "from": "/rows/17/citationUse",
          "to": "/rows/989/citationUse"
        },
        "reviewerName": {
          "from": "/rows/17/reviewerName",
          "to": "/rows/989/reviewerName"
        },
        "reviewedAt": {
          "from": "/rows/17/reviewedAt",
          "to": "/rows/989/reviewedAt"
        },
        "realHumanInput": {
          "from": "/rows/17/realHumanInput",
          "to": "/rows/989/realHumanInput"
        }
      }
    },
    {
      "packetRowIndex": 18,
      "targetFullDraftRowIndex": 1056,
      "reviewId": "knv2_0263::corpus_0423",
      "nodeId": "knv2_0263",
      "documentId": "corpus_0423",
      "sourceName": "Wikipedia: Diversification (finance)",
      "mappedToFullDraft": true,
      "packetValidationStatus": "blocked_missing_or_invalid_reviewer_input",
      "readyForMerge": false,
      "mergeBlockedReason": "packet_row_not_ready_for_merge",
      "fieldCopyPlan": {
        "reviewerDecision": {
          "from": "/rows/18/reviewerDecision",
          "to": "/rows/1056/reviewerDecision"
        },
        "sourceFitNotes": {
          "from": "/rows/18/sourceFitNotes",
          "to": "/rows/1056/sourceFitNotes"
        },
        "citationUse": {
          "from": "/rows/18/citationUse",
          "to": "/rows/1056/citationUse"
        },
        "reviewerName": {
          "from": "/rows/18/reviewerName",
          "to": "/rows/1056/reviewerName"
        },
        "reviewedAt": {
          "from": "/rows/18/reviewedAt",
          "to": "/rows/1056/reviewedAt"
        },
        "realHumanInput": {
          "from": "/rows/18/realHumanInput",
          "to": "/rows/1056/realHumanInput"
        }
      }
    },
    {
      "packetRowIndex": 19,
      "targetFullDraftRowIndex": 1057,
      "reviewId": "knv2_0263::corpus_0042",
      "nodeId": "knv2_0263",
      "documentId": "corpus_0042",
      "sourceName": "CFTC Speculative Limits",
      "mappedToFullDraft": true,
      "packetValidationStatus": "blocked_missing_or_invalid_reviewer_input",
      "readyForMerge": false,
      "mergeBlockedReason": "packet_row_not_ready_for_merge",
      "fieldCopyPlan": {
        "reviewerDecision": {
          "from": "/rows/19/reviewerDecision",
          "to": "/rows/1057/reviewerDecision"
        },
        "sourceFitNotes": {
          "from": "/rows/19/sourceFitNotes",
          "to": "/rows/1057/sourceFitNotes"
        },
        "citationUse": {
          "from": "/rows/19/citationUse",
          "to": "/rows/1057/citationUse"
        },
        "reviewerName": {
          "from": "/rows/19/reviewerName",
          "to": "/rows/1057/reviewerName"
        },
        "reviewedAt": {
          "from": "/rows/19/reviewedAt",
          "to": "/rows/1057/reviewedAt"
        },
        "realHumanInput": {
          "from": "/rows/19/realHumanInput",
          "to": "/rows/1057/realHumanInput"
        }
      }
    },
    {
      "packetRowIndex": 20,
      "targetFullDraftRowIndex": 1058,
      "reviewId": "knv2_0263::corpus_0646",
      "nodeId": "knv2_0263",
      "documentId": "corpus_0646",
      "sourceName": "A note on estimating stochastic volatility and its volatility: a new simple method",
      "mappedToFullDraft": true,
      "packetValidationStatus": "blocked_missing_or_invalid_reviewer_input",
      "readyForMerge": false,
      "mergeBlockedReason": "packet_row_not_ready_for_merge",
      "fieldCopyPlan": {
        "reviewerDecision": {
          "from": "/rows/20/reviewerDecision",
          "to": "/rows/1058/reviewerDecision"
        },
        "sourceFitNotes": {
          "from": "/rows/20/sourceFitNotes",
          "to": "/rows/1058/sourceFitNotes"
        },
        "citationUse": {
          "from": "/rows/20/citationUse",
          "to": "/rows/1058/citationUse"
        },
        "reviewerName": {
          "from": "/rows/20/reviewerName",
          "to": "/rows/1058/reviewerName"
        },
        "reviewedAt": {
          "from": "/rows/20/reviewedAt",
          "to": "/rows/1058/reviewedAt"
        },
        "realHumanInput": {
          "from": "/rows/20/realHumanInput",
          "to": "/rows/1058/realHumanInput"
        }
      }
    },
    {
      "packetRowIndex": 21,
      "targetFullDraftRowIndex": 1059,
      "reviewId": "knv2_0263::corpus_0422",
      "nodeId": "knv2_0263",
      "documentId": "corpus_0422",
      "sourceName": "Wikipedia: Drawdown (economics)",
      "mappedToFullDraft": true,
      "packetValidationStatus": "blocked_missing_or_invalid_reviewer_input",
      "readyForMerge": false,
      "mergeBlockedReason": "packet_row_not_ready_for_merge",
      "fieldCopyPlan": {
        "reviewerDecision": {
          "from": "/rows/21/reviewerDecision",
          "to": "/rows/1059/reviewerDecision"
        },
        "sourceFitNotes": {
          "from": "/rows/21/sourceFitNotes",
          "to": "/rows/1059/sourceFitNotes"
        },
        "citationUse": {
          "from": "/rows/21/citationUse",
          "to": "/rows/1059/citationUse"
        },
        "reviewerName": {
          "from": "/rows/21/reviewerName",
          "to": "/rows/1059/reviewerName"
        },
        "reviewedAt": {
          "from": "/rows/21/reviewedAt",
          "to": "/rows/1059/reviewedAt"
        },
        "realHumanInput": {
          "from": "/rows/21/realHumanInput",
          "to": "/rows/1059/realHumanInput"
        }
      }
    },
    {
      "packetRowIndex": 22,
      "targetFullDraftRowIndex": 1060,
      "reviewId": "knv2_0263::corpus_0421",
      "nodeId": "knv2_0263",
      "documentId": "corpus_0421",
      "sourceName": "Wikipedia: Kelly criterion",
      "mappedToFullDraft": true,
      "packetValidationStatus": "blocked_missing_or_invalid_reviewer_input",
      "readyForMerge": false,
      "mergeBlockedReason": "packet_row_not_ready_for_merge",
      "fieldCopyPlan": {
        "reviewerDecision": {
          "from": "/rows/22/reviewerDecision",
          "to": "/rows/1060/reviewerDecision"
        },
        "sourceFitNotes": {
          "from": "/rows/22/sourceFitNotes",
          "to": "/rows/1060/sourceFitNotes"
        },
        "citationUse": {
          "from": "/rows/22/citationUse",
          "to": "/rows/1060/citationUse"
        },
        "reviewerName": {
          "from": "/rows/22/reviewerName",
          "to": "/rows/1060/reviewerName"
        },
        "reviewedAt": {
          "from": "/rows/22/reviewedAt",
          "to": "/rows/1060/reviewedAt"
        },
        "realHumanInput": {
          "from": "/rows/22/realHumanInput",
          "to": "/rows/1060/realHumanInput"
        }
      }
    },
    {
      "packetRowIndex": 23,
      "targetFullDraftRowIndex": 1061,
      "reviewId": "knv2_0263::corpus_0458",
      "nodeId": "knv2_0263",
      "documentId": "corpus_0458",
      "sourceName": "Wikipedia: Leverage (finance)",
      "mappedToFullDraft": true,
      "packetValidationStatus": "blocked_missing_or_invalid_reviewer_input",
      "readyForMerge": false,
      "mergeBlockedReason": "packet_row_not_ready_for_merge",
      "fieldCopyPlan": {
        "reviewerDecision": {
          "from": "/rows/23/reviewerDecision",
          "to": "/rows/1061/reviewerDecision"
        },
        "sourceFitNotes": {
          "from": "/rows/23/sourceFitNotes",
          "to": "/rows/1061/sourceFitNotes"
        },
        "citationUse": {
          "from": "/rows/23/citationUse",
          "to": "/rows/1061/citationUse"
        },
        "reviewerName": {
          "from": "/rows/23/reviewerName",
          "to": "/rows/1061/reviewerName"
        },
        "reviewedAt": {
          "from": "/rows/23/reviewedAt",
          "to": "/rows/1061/reviewedAt"
        },
        "realHumanInput": {
          "from": "/rows/23/realHumanInput",
          "to": "/rows/1061/realHumanInput"
        }
      }
    },
    {
      "packetRowIndex": 24,
      "targetFullDraftRowIndex": 1128,
      "reviewId": "knv2_0275::corpus_0423",
      "nodeId": "knv2_0275",
      "documentId": "corpus_0423",
      "sourceName": "Wikipedia: Diversification (finance)",
      "mappedToFullDraft": true,
      "packetValidationStatus": "blocked_missing_or_invalid_reviewer_input",
      "readyForMerge": false,
      "mergeBlockedReason": "packet_row_not_ready_for_merge",
      "fieldCopyPlan": {
        "reviewerDecision": {
          "from": "/rows/24/reviewerDecision",
          "to": "/rows/1128/reviewerDecision"
        },
        "sourceFitNotes": {
          "from": "/rows/24/sourceFitNotes",
          "to": "/rows/1128/sourceFitNotes"
        },
        "citationUse": {
          "from": "/rows/24/citationUse",
          "to": "/rows/1128/citationUse"
        },
        "reviewerName": {
          "from": "/rows/24/reviewerName",
          "to": "/rows/1128/reviewerName"
        },
        "reviewedAt": {
          "from": "/rows/24/reviewedAt",
          "to": "/rows/1128/reviewedAt"
        },
        "realHumanInput": {
          "from": "/rows/24/realHumanInput",
          "to": "/rows/1128/realHumanInput"
        }
      }
    },
    {
      "packetRowIndex": 25,
      "targetFullDraftRowIndex": 1129,
      "reviewId": "knv2_0275::corpus_0042",
      "nodeId": "knv2_0275",
      "documentId": "corpus_0042",
      "sourceName": "CFTC Speculative Limits",
      "mappedToFullDraft": true,
      "packetValidationStatus": "blocked_missing_or_invalid_reviewer_input",
      "readyForMerge": false,
      "mergeBlockedReason": "packet_row_not_ready_for_merge",
      "fieldCopyPlan": {
        "reviewerDecision": {
          "from": "/rows/25/reviewerDecision",
          "to": "/rows/1129/reviewerDecision"
        },
        "sourceFitNotes": {
          "from": "/rows/25/sourceFitNotes",
          "to": "/rows/1129/sourceFitNotes"
        },
        "citationUse": {
          "from": "/rows/25/citationUse",
          "to": "/rows/1129/citationUse"
        },
        "reviewerName": {
          "from": "/rows/25/reviewerName",
          "to": "/rows/1129/reviewerName"
        },
        "reviewedAt": {
          "from": "/rows/25/reviewedAt",
          "to": "/rows/1129/reviewedAt"
        },
        "realHumanInput": {
          "from": "/rows/25/realHumanInput",
          "to": "/rows/1129/realHumanInput"
        }
      }
    },
    {
      "packetRowIndex": 26,
      "targetFullDraftRowIndex": 1130,
      "reviewId": "knv2_0275::corpus_0646",
      "nodeId": "knv2_0275",
      "documentId": "corpus_0646",
      "sourceName": "A note on estimating stochastic volatility and its volatility: a new simple method",
      "mappedToFullDraft": true,
      "packetValidationStatus": "blocked_missing_or_invalid_reviewer_input",
      "readyForMerge": false,
      "mergeBlockedReason": "packet_row_not_ready_for_merge",
      "fieldCopyPlan": {
        "reviewerDecision": {
          "from": "/rows/26/reviewerDecision",
          "to": "/rows/1130/reviewerDecision"
        },
        "sourceFitNotes": {
          "from": "/rows/26/sourceFitNotes",
          "to": "/rows/1130/sourceFitNotes"
        },
        "citationUse": {
          "from": "/rows/26/citationUse",
          "to": "/rows/1130/citationUse"
        },
        "reviewerName": {
          "from": "/rows/26/reviewerName",
          "to": "/rows/1130/reviewerName"
        },
        "reviewedAt": {
          "from": "/rows/26/reviewedAt",
          "to": "/rows/1130/reviewedAt"
        },
        "realHumanInput": {
          "from": "/rows/26/realHumanInput",
          "to": "/rows/1130/realHumanInput"
        }
      }
    },
    {
      "packetRowIndex": 27,
      "targetFullDraftRowIndex": 1131,
      "reviewId": "knv2_0275::corpus_0422",
      "nodeId": "knv2_0275",
      "documentId": "corpus_0422",
      "sourceName": "Wikipedia: Drawdown (economics)",
      "mappedToFullDraft": true,
      "packetValidationStatus": "blocked_missing_or_invalid_reviewer_input",
      "readyForMerge": false,
      "mergeBlockedReason": "packet_row_not_ready_for_merge",
      "fieldCopyPlan": {
        "reviewerDecision": {
          "from": "/rows/27/reviewerDecision",
          "to": "/rows/1131/reviewerDecision"
        },
        "sourceFitNotes": {
          "from": "/rows/27/sourceFitNotes",
          "to": "/rows/1131/sourceFitNotes"
        },
        "citationUse": {
          "from": "/rows/27/citationUse",
          "to": "/rows/1131/citationUse"
        },
        "reviewerName": {
          "from": "/rows/27/reviewerName",
          "to": "/rows/1131/reviewerName"
        },
        "reviewedAt": {
          "from": "/rows/27/reviewedAt",
          "to": "/rows/1131/reviewedAt"
        },
        "realHumanInput": {
          "from": "/rows/27/realHumanInput",
          "to": "/rows/1131/realHumanInput"
        }
      }
    },
    {
      "packetRowIndex": 28,
      "targetFullDraftRowIndex": 1132,
      "reviewId": "knv2_0275::corpus_0421",
      "nodeId": "knv2_0275",
      "documentId": "corpus_0421",
      "sourceName": "Wikipedia: Kelly criterion",
      "mappedToFullDraft": true,
      "packetValidationStatus": "blocked_missing_or_invalid_reviewer_input",
      "readyForMerge": false,
      "mergeBlockedReason": "packet_row_not_ready_for_merge",
      "fieldCopyPlan": {
        "reviewerDecision": {
          "from": "/rows/28/reviewerDecision",
          "to": "/rows/1132/reviewerDecision"
        },
        "sourceFitNotes": {
          "from": "/rows/28/sourceFitNotes",
          "to": "/rows/1132/sourceFitNotes"
        },
        "citationUse": {
          "from": "/rows/28/citationUse",
          "to": "/rows/1132/citationUse"
        },
        "reviewerName": {
          "from": "/rows/28/reviewerName",
          "to": "/rows/1132/reviewerName"
        },
        "reviewedAt": {
          "from": "/rows/28/reviewedAt",
          "to": "/rows/1132/reviewedAt"
        },
        "realHumanInput": {
          "from": "/rows/28/realHumanInput",
          "to": "/rows/1132/realHumanInput"
        }
      }
    },
    {
      "packetRowIndex": 29,
      "targetFullDraftRowIndex": 1133,
      "reviewId": "knv2_0275::corpus_0458",
      "nodeId": "knv2_0275",
      "documentId": "corpus_0458",
      "sourceName": "Wikipedia: Leverage (finance)",
      "mappedToFullDraft": true,
      "packetValidationStatus": "blocked_missing_or_invalid_reviewer_input",
      "readyForMerge": false,
      "mergeBlockedReason": "packet_row_not_ready_for_merge",
      "fieldCopyPlan": {
        "reviewerDecision": {
          "from": "/rows/29/reviewerDecision",
          "to": "/rows/1133/reviewerDecision"
        },
        "sourceFitNotes": {
          "from": "/rows/29/sourceFitNotes",
          "to": "/rows/1133/sourceFitNotes"
        },
        "citationUse": {
          "from": "/rows/29/citationUse",
          "to": "/rows/1133/citationUse"
        },
        "reviewerName": {
          "from": "/rows/29/reviewerName",
          "to": "/rows/1133/reviewerName"
        },
        "reviewedAt": {
          "from": "/rows/29/reviewedAt",
          "to": "/rows/1133/reviewedAt"
        },
        "realHumanInput": {
          "from": "/rows/29/realHumanInput",
          "to": "/rows/1133/realHumanInput"
        }
      }
    },
    {
      "packetRowIndex": 30,
      "targetFullDraftRowIndex": 1200,
      "reviewId": "knv2_0287::corpus_0423",
      "nodeId": "knv2_0287",
      "documentId": "corpus_0423",
      "sourceName": "Wikipedia: Diversification (finance)",
      "mappedToFullDraft": true,
      "packetValidationStatus": "blocked_missing_or_invalid_reviewer_input",
      "readyForMerge": false,
      "mergeBlockedReason": "packet_row_not_ready_for_merge",
      "fieldCopyPlan": {
        "reviewerDecision": {
          "from": "/rows/30/reviewerDecision",
          "to": "/rows/1200/reviewerDecision"
        },
        "sourceFitNotes": {
          "from": "/rows/30/sourceFitNotes",
          "to": "/rows/1200/sourceFitNotes"
        },
        "citationUse": {
          "from": "/rows/30/citationUse",
          "to": "/rows/1200/citationUse"
        },
        "reviewerName": {
          "from": "/rows/30/reviewerName",
          "to": "/rows/1200/reviewerName"
        },
        "reviewedAt": {
          "from": "/rows/30/reviewedAt",
          "to": "/rows/1200/reviewedAt"
        },
        "realHumanInput": {
          "from": "/rows/30/realHumanInput",
          "to": "/rows/1200/realHumanInput"
        }
      }
    },
    {
      "packetRowIndex": 31,
      "targetFullDraftRowIndex": 1201,
      "reviewId": "knv2_0287::corpus_0042",
      "nodeId": "knv2_0287",
      "documentId": "corpus_0042",
      "sourceName": "CFTC Speculative Limits",
      "mappedToFullDraft": true,
      "packetValidationStatus": "blocked_missing_or_invalid_reviewer_input",
      "readyForMerge": false,
      "mergeBlockedReason": "packet_row_not_ready_for_merge",
      "fieldCopyPlan": {
        "reviewerDecision": {
          "from": "/rows/31/reviewerDecision",
          "to": "/rows/1201/reviewerDecision"
        },
        "sourceFitNotes": {
          "from": "/rows/31/sourceFitNotes",
          "to": "/rows/1201/sourceFitNotes"
        },
        "citationUse": {
          "from": "/rows/31/citationUse",
          "to": "/rows/1201/citationUse"
        },
        "reviewerName": {
          "from": "/rows/31/reviewerName",
          "to": "/rows/1201/reviewerName"
        },
        "reviewedAt": {
          "from": "/rows/31/reviewedAt",
          "to": "/rows/1201/reviewedAt"
        },
        "realHumanInput": {
          "from": "/rows/31/realHumanInput",
          "to": "/rows/1201/realHumanInput"
        }
      }
    },
    {
      "packetRowIndex": 32,
      "targetFullDraftRowIndex": 1202,
      "reviewId": "knv2_0287::corpus_0646",
      "nodeId": "knv2_0287",
      "documentId": "corpus_0646",
      "sourceName": "A note on estimating stochastic volatility and its volatility: a new simple method",
      "mappedToFullDraft": true,
      "packetValidationStatus": "blocked_missing_or_invalid_reviewer_input",
      "readyForMerge": false,
      "mergeBlockedReason": "packet_row_not_ready_for_merge",
      "fieldCopyPlan": {
        "reviewerDecision": {
          "from": "/rows/32/reviewerDecision",
          "to": "/rows/1202/reviewerDecision"
        },
        "sourceFitNotes": {
          "from": "/rows/32/sourceFitNotes",
          "to": "/rows/1202/sourceFitNotes"
        },
        "citationUse": {
          "from": "/rows/32/citationUse",
          "to": "/rows/1202/citationUse"
        },
        "reviewerName": {
          "from": "/rows/32/reviewerName",
          "to": "/rows/1202/reviewerName"
        },
        "reviewedAt": {
          "from": "/rows/32/reviewedAt",
          "to": "/rows/1202/reviewedAt"
        },
        "realHumanInput": {
          "from": "/rows/32/realHumanInput",
          "to": "/rows/1202/realHumanInput"
        }
      }
    },
    {
      "packetRowIndex": 33,
      "targetFullDraftRowIndex": 1203,
      "reviewId": "knv2_0287::corpus_0422",
      "nodeId": "knv2_0287",
      "documentId": "corpus_0422",
      "sourceName": "Wikipedia: Drawdown (economics)",
      "mappedToFullDraft": true,
      "packetValidationStatus": "blocked_missing_or_invalid_reviewer_input",
      "readyForMerge": false,
      "mergeBlockedReason": "packet_row_not_ready_for_merge",
      "fieldCopyPlan": {
        "reviewerDecision": {
          "from": "/rows/33/reviewerDecision",
          "to": "/rows/1203/reviewerDecision"
        },
        "sourceFitNotes": {
          "from": "/rows/33/sourceFitNotes",
          "to": "/rows/1203/sourceFitNotes"
        },
        "citationUse": {
          "from": "/rows/33/citationUse",
          "to": "/rows/1203/citationUse"
        },
        "reviewerName": {
          "from": "/rows/33/reviewerName",
          "to": "/rows/1203/reviewerName"
        },
        "reviewedAt": {
          "from": "/rows/33/reviewedAt",
          "to": "/rows/1203/reviewedAt"
        },
        "realHumanInput": {
          "from": "/rows/33/realHumanInput",
          "to": "/rows/1203/realHumanInput"
        }
      }
    },
    {
      "packetRowIndex": 34,
      "targetFullDraftRowIndex": 1204,
      "reviewId": "knv2_0287::corpus_0421",
      "nodeId": "knv2_0287",
      "documentId": "corpus_0421",
      "sourceName": "Wikipedia: Kelly criterion",
      "mappedToFullDraft": true,
      "packetValidationStatus": "blocked_missing_or_invalid_reviewer_input",
      "readyForMerge": false,
      "mergeBlockedReason": "packet_row_not_ready_for_merge",
      "fieldCopyPlan": {
        "reviewerDecision": {
          "from": "/rows/34/reviewerDecision",
          "to": "/rows/1204/reviewerDecision"
        },
        "sourceFitNotes": {
          "from": "/rows/34/sourceFitNotes",
          "to": "/rows/1204/sourceFitNotes"
        },
        "citationUse": {
          "from": "/rows/34/citationUse",
          "to": "/rows/1204/citationUse"
        },
        "reviewerName": {
          "from": "/rows/34/reviewerName",
          "to": "/rows/1204/reviewerName"
        },
        "reviewedAt": {
          "from": "/rows/34/reviewedAt",
          "to": "/rows/1204/reviewedAt"
        },
        "realHumanInput": {
          "from": "/rows/34/realHumanInput",
          "to": "/rows/1204/realHumanInput"
        }
      }
    },
    {
      "packetRowIndex": 35,
      "targetFullDraftRowIndex": 1205,
      "reviewId": "knv2_0287::corpus_0458",
      "nodeId": "knv2_0287",
      "documentId": "corpus_0458",
      "sourceName": "Wikipedia: Leverage (finance)",
      "mappedToFullDraft": true,
      "packetValidationStatus": "blocked_missing_or_invalid_reviewer_input",
      "readyForMerge": false,
      "mergeBlockedReason": "packet_row_not_ready_for_merge",
      "fieldCopyPlan": {
        "reviewerDecision": {
          "from": "/rows/35/reviewerDecision",
          "to": "/rows/1205/reviewerDecision"
        },
        "sourceFitNotes": {
          "from": "/rows/35/sourceFitNotes",
          "to": "/rows/1205/sourceFitNotes"
        },
        "citationUse": {
          "from": "/rows/35/citationUse",
          "to": "/rows/1205/citationUse"
        },
        "reviewerName": {
          "from": "/rows/35/reviewerName",
          "to": "/rows/1205/reviewerName"
        },
        "reviewedAt": {
          "from": "/rows/35/reviewedAt",
          "to": "/rows/1205/reviewedAt"
        },
        "realHumanInput": {
          "from": "/rows/35/realHumanInput",
          "to": "/rows/1205/realHumanInput"
        }
      }
    },
    {
      "packetRowIndex": 36,
      "targetFullDraftRowIndex": 1272,
      "reviewId": "knv2_0299::corpus_0423",
      "nodeId": "knv2_0299",
      "documentId": "corpus_0423",
      "sourceName": "Wikipedia: Diversification (finance)",
      "mappedToFullDraft": true,
      "packetValidationStatus": "blocked_missing_or_invalid_reviewer_input",
      "readyForMerge": false,
      "mergeBlockedReason": "packet_row_not_ready_for_merge",
      "fieldCopyPlan": {
        "reviewerDecision": {
          "from": "/rows/36/reviewerDecision",
          "to": "/rows/1272/reviewerDecision"
        },
        "sourceFitNotes": {
          "from": "/rows/36/sourceFitNotes",
          "to": "/rows/1272/sourceFitNotes"
        },
        "citationUse": {
          "from": "/rows/36/citationUse",
          "to": "/rows/1272/citationUse"
        },
        "reviewerName": {
          "from": "/rows/36/reviewerName",
          "to": "/rows/1272/reviewerName"
        },
        "reviewedAt": {
          "from": "/rows/36/reviewedAt",
          "to": "/rows/1272/reviewedAt"
        },
        "realHumanInput": {
          "from": "/rows/36/realHumanInput",
          "to": "/rows/1272/realHumanInput"
        }
      }
    },
    {
      "packetRowIndex": 37,
      "targetFullDraftRowIndex": 1273,
      "reviewId": "knv2_0299::corpus_0042",
      "nodeId": "knv2_0299",
      "documentId": "corpus_0042",
      "sourceName": "CFTC Speculative Limits",
      "mappedToFullDraft": true,
      "packetValidationStatus": "blocked_missing_or_invalid_reviewer_input",
      "readyForMerge": false,
      "mergeBlockedReason": "packet_row_not_ready_for_merge",
      "fieldCopyPlan": {
        "reviewerDecision": {
          "from": "/rows/37/reviewerDecision",
          "to": "/rows/1273/reviewerDecision"
        },
        "sourceFitNotes": {
          "from": "/rows/37/sourceFitNotes",
          "to": "/rows/1273/sourceFitNotes"
        },
        "citationUse": {
          "from": "/rows/37/citationUse",
          "to": "/rows/1273/citationUse"
        },
        "reviewerName": {
          "from": "/rows/37/reviewerName",
          "to": "/rows/1273/reviewerName"
        },
        "reviewedAt": {
          "from": "/rows/37/reviewedAt",
          "to": "/rows/1273/reviewedAt"
        },
        "realHumanInput": {
          "from": "/rows/37/realHumanInput",
          "to": "/rows/1273/realHumanInput"
        }
      }
    },
    {
      "packetRowIndex": 38,
      "targetFullDraftRowIndex": 1274,
      "reviewId": "knv2_0299::corpus_0646",
      "nodeId": "knv2_0299",
      "documentId": "corpus_0646",
      "sourceName": "A note on estimating stochastic volatility and its volatility: a new simple method",
      "mappedToFullDraft": true,
      "packetValidationStatus": "blocked_missing_or_invalid_reviewer_input",
      "readyForMerge": false,
      "mergeBlockedReason": "packet_row_not_ready_for_merge",
      "fieldCopyPlan": {
        "reviewerDecision": {
          "from": "/rows/38/reviewerDecision",
          "to": "/rows/1274/reviewerDecision"
        },
        "sourceFitNotes": {
          "from": "/rows/38/sourceFitNotes",
          "to": "/rows/1274/sourceFitNotes"
        },
        "citationUse": {
          "from": "/rows/38/citationUse",
          "to": "/rows/1274/citationUse"
        },
        "reviewerName": {
          "from": "/rows/38/reviewerName",
          "to": "/rows/1274/reviewerName"
        },
        "reviewedAt": {
          "from": "/rows/38/reviewedAt",
          "to": "/rows/1274/reviewedAt"
        },
        "realHumanInput": {
          "from": "/rows/38/realHumanInput",
          "to": "/rows/1274/realHumanInput"
        }
      }
    },
    {
      "packetRowIndex": 39,
      "targetFullDraftRowIndex": 1275,
      "reviewId": "knv2_0299::corpus_0422",
      "nodeId": "knv2_0299",
      "documentId": "corpus_0422",
      "sourceName": "Wikipedia: Drawdown (economics)",
      "mappedToFullDraft": true,
      "packetValidationStatus": "blocked_missing_or_invalid_reviewer_input",
      "readyForMerge": false,
      "mergeBlockedReason": "packet_row_not_ready_for_merge",
      "fieldCopyPlan": {
        "reviewerDecision": {
          "from": "/rows/39/reviewerDecision",
          "to": "/rows/1275/reviewerDecision"
        },
        "sourceFitNotes": {
          "from": "/rows/39/sourceFitNotes",
          "to": "/rows/1275/sourceFitNotes"
        },
        "citationUse": {
          "from": "/rows/39/citationUse",
          "to": "/rows/1275/citationUse"
        },
        "reviewerName": {
          "from": "/rows/39/reviewerName",
          "to": "/rows/1275/reviewerName"
        },
        "reviewedAt": {
          "from": "/rows/39/reviewedAt",
          "to": "/rows/1275/reviewedAt"
        },
        "realHumanInput": {
          "from": "/rows/39/realHumanInput",
          "to": "/rows/1275/realHumanInput"
        }
      }
    },
    {
      "packetRowIndex": 40,
      "targetFullDraftRowIndex": 1276,
      "reviewId": "knv2_0299::corpus_0421",
      "nodeId": "knv2_0299",
      "documentId": "corpus_0421",
      "sourceName": "Wikipedia: Kelly criterion",
      "mappedToFullDraft": true,
      "packetValidationStatus": "blocked_missing_or_invalid_reviewer_input",
      "readyForMerge": false,
      "mergeBlockedReason": "packet_row_not_ready_for_merge",
      "fieldCopyPlan": {
        "reviewerDecision": {
          "from": "/rows/40/reviewerDecision",
          "to": "/rows/1276/reviewerDecision"
        },
        "sourceFitNotes": {
          "from": "/rows/40/sourceFitNotes",
          "to": "/rows/1276/sourceFitNotes"
        },
        "citationUse": {
          "from": "/rows/40/citationUse",
          "to": "/rows/1276/citationUse"
        },
        "reviewerName": {
          "from": "/rows/40/reviewerName",
          "to": "/rows/1276/reviewerName"
        },
        "reviewedAt": {
          "from": "/rows/40/reviewedAt",
          "to": "/rows/1276/reviewedAt"
        },
        "realHumanInput": {
          "from": "/rows/40/realHumanInput",
          "to": "/rows/1276/realHumanInput"
        }
      }
    },
    {
      "packetRowIndex": 41,
      "targetFullDraftRowIndex": 1277,
      "reviewId": "knv2_0299::corpus_0458",
      "nodeId": "knv2_0299",
      "documentId": "corpus_0458",
      "sourceName": "Wikipedia: Leverage (finance)",
      "mappedToFullDraft": true,
      "packetValidationStatus": "blocked_missing_or_invalid_reviewer_input",
      "readyForMerge": false,
      "mergeBlockedReason": "packet_row_not_ready_for_merge",
      "fieldCopyPlan": {
        "reviewerDecision": {
          "from": "/rows/41/reviewerDecision",
          "to": "/rows/1277/reviewerDecision"
        },
        "sourceFitNotes": {
          "from": "/rows/41/sourceFitNotes",
          "to": "/rows/1277/sourceFitNotes"
        },
        "citationUse": {
          "from": "/rows/41/citationUse",
          "to": "/rows/1277/citationUse"
        },
        "reviewerName": {
          "from": "/rows/41/reviewerName",
          "to": "/rows/1277/reviewerName"
        },
        "reviewedAt": {
          "from": "/rows/41/reviewedAt",
          "to": "/rows/1277/reviewedAt"
        },
        "realHumanInput": {
          "from": "/rows/41/realHumanInput",
          "to": "/rows/1277/realHumanInput"
        }
      }
    },
    {
      "packetRowIndex": 42,
      "targetFullDraftRowIndex": 1338,
      "reviewId": "knv2_0311::corpus_0423",
      "nodeId": "knv2_0311",
      "documentId": "corpus_0423",
      "sourceName": "Wikipedia: Diversification (finance)",
      "mappedToFullDraft": true,
      "packetValidationStatus": "blocked_missing_or_invalid_reviewer_input",
      "readyForMerge": false,
      "mergeBlockedReason": "packet_row_not_ready_for_merge",
      "fieldCopyPlan": {
        "reviewerDecision": {
          "from": "/rows/42/reviewerDecision",
          "to": "/rows/1338/reviewerDecision"
        },
        "sourceFitNotes": {
          "from": "/rows/42/sourceFitNotes",
          "to": "/rows/1338/sourceFitNotes"
        },
        "citationUse": {
          "from": "/rows/42/citationUse",
          "to": "/rows/1338/citationUse"
        },
        "reviewerName": {
          "from": "/rows/42/reviewerName",
          "to": "/rows/1338/reviewerName"
        },
        "reviewedAt": {
          "from": "/rows/42/reviewedAt",
          "to": "/rows/1338/reviewedAt"
        },
        "realHumanInput": {
          "from": "/rows/42/realHumanInput",
          "to": "/rows/1338/realHumanInput"
        }
      }
    },
    {
      "packetRowIndex": 43,
      "targetFullDraftRowIndex": 1339,
      "reviewId": "knv2_0311::corpus_0042",
      "nodeId": "knv2_0311",
      "documentId": "corpus_0042",
      "sourceName": "CFTC Speculative Limits",
      "mappedToFullDraft": true,
      "packetValidationStatus": "blocked_missing_or_invalid_reviewer_input",
      "readyForMerge": false,
      "mergeBlockedReason": "packet_row_not_ready_for_merge",
      "fieldCopyPlan": {
        "reviewerDecision": {
          "from": "/rows/43/reviewerDecision",
          "to": "/rows/1339/reviewerDecision"
        },
        "sourceFitNotes": {
          "from": "/rows/43/sourceFitNotes",
          "to": "/rows/1339/sourceFitNotes"
        },
        "citationUse": {
          "from": "/rows/43/citationUse",
          "to": "/rows/1339/citationUse"
        },
        "reviewerName": {
          "from": "/rows/43/reviewerName",
          "to": "/rows/1339/reviewerName"
        },
        "reviewedAt": {
          "from": "/rows/43/reviewedAt",
          "to": "/rows/1339/reviewedAt"
        },
        "realHumanInput": {
          "from": "/rows/43/realHumanInput",
          "to": "/rows/1339/realHumanInput"
        }
      }
    },
    {
      "packetRowIndex": 44,
      "targetFullDraftRowIndex": 1340,
      "reviewId": "knv2_0311::corpus_0646",
      "nodeId": "knv2_0311",
      "documentId": "corpus_0646",
      "sourceName": "A note on estimating stochastic volatility and its volatility: a new simple method",
      "mappedToFullDraft": true,
      "packetValidationStatus": "blocked_missing_or_invalid_reviewer_input",
      "readyForMerge": false,
      "mergeBlockedReason": "packet_row_not_ready_for_merge",
      "fieldCopyPlan": {
        "reviewerDecision": {
          "from": "/rows/44/reviewerDecision",
          "to": "/rows/1340/reviewerDecision"
        },
        "sourceFitNotes": {
          "from": "/rows/44/sourceFitNotes",
          "to": "/rows/1340/sourceFitNotes"
        },
        "citationUse": {
          "from": "/rows/44/citationUse",
          "to": "/rows/1340/citationUse"
        },
        "reviewerName": {
          "from": "/rows/44/reviewerName",
          "to": "/rows/1340/reviewerName"
        },
        "reviewedAt": {
          "from": "/rows/44/reviewedAt",
          "to": "/rows/1340/reviewedAt"
        },
        "realHumanInput": {
          "from": "/rows/44/realHumanInput",
          "to": "/rows/1340/realHumanInput"
        }
      }
    },
    {
      "packetRowIndex": 45,
      "targetFullDraftRowIndex": 1341,
      "reviewId": "knv2_0311::corpus_0422",
      "nodeId": "knv2_0311",
      "documentId": "corpus_0422",
      "sourceName": "Wikipedia: Drawdown (economics)",
      "mappedToFullDraft": true,
      "packetValidationStatus": "blocked_missing_or_invalid_reviewer_input",
      "readyForMerge": false,
      "mergeBlockedReason": "packet_row_not_ready_for_merge",
      "fieldCopyPlan": {
        "reviewerDecision": {
          "from": "/rows/45/reviewerDecision",
          "to": "/rows/1341/reviewerDecision"
        },
        "sourceFitNotes": {
          "from": "/rows/45/sourceFitNotes",
          "to": "/rows/1341/sourceFitNotes"
        },
        "citationUse": {
          "from": "/rows/45/citationUse",
          "to": "/rows/1341/citationUse"
        },
        "reviewerName": {
          "from": "/rows/45/reviewerName",
          "to": "/rows/1341/reviewerName"
        },
        "reviewedAt": {
          "from": "/rows/45/reviewedAt",
          "to": "/rows/1341/reviewedAt"
        },
        "realHumanInput": {
          "from": "/rows/45/realHumanInput",
          "to": "/rows/1341/realHumanInput"
        }
      }
    },
    {
      "packetRowIndex": 46,
      "targetFullDraftRowIndex": 1342,
      "reviewId": "knv2_0311::corpus_0421",
      "nodeId": "knv2_0311",
      "documentId": "corpus_0421",
      "sourceName": "Wikipedia: Kelly criterion",
      "mappedToFullDraft": true,
      "packetValidationStatus": "blocked_missing_or_invalid_reviewer_input",
      "readyForMerge": false,
      "mergeBlockedReason": "packet_row_not_ready_for_merge",
      "fieldCopyPlan": {
        "reviewerDecision": {
          "from": "/rows/46/reviewerDecision",
          "to": "/rows/1342/reviewerDecision"
        },
        "sourceFitNotes": {
          "from": "/rows/46/sourceFitNotes",
          "to": "/rows/1342/sourceFitNotes"
        },
        "citationUse": {
          "from": "/rows/46/citationUse",
          "to": "/rows/1342/citationUse"
        },
        "reviewerName": {
          "from": "/rows/46/reviewerName",
          "to": "/rows/1342/reviewerName"
        },
        "reviewedAt": {
          "from": "/rows/46/reviewedAt",
          "to": "/rows/1342/reviewedAt"
        },
        "realHumanInput": {
          "from": "/rows/46/realHumanInput",
          "to": "/rows/1342/realHumanInput"
        }
      }
    },
    {
      "packetRowIndex": 47,
      "targetFullDraftRowIndex": 1343,
      "reviewId": "knv2_0311::corpus_0458",
      "nodeId": "knv2_0311",
      "documentId": "corpus_0458",
      "sourceName": "Wikipedia: Leverage (finance)",
      "mappedToFullDraft": true,
      "packetValidationStatus": "blocked_missing_or_invalid_reviewer_input",
      "readyForMerge": false,
      "mergeBlockedReason": "packet_row_not_ready_for_merge",
      "fieldCopyPlan": {
        "reviewerDecision": {
          "from": "/rows/47/reviewerDecision",
          "to": "/rows/1343/reviewerDecision"
        },
        "sourceFitNotes": {
          "from": "/rows/47/sourceFitNotes",
          "to": "/rows/1343/sourceFitNotes"
        },
        "citationUse": {
          "from": "/rows/47/citationUse",
          "to": "/rows/1343/citationUse"
        },
        "reviewerName": {
          "from": "/rows/47/reviewerName",
          "to": "/rows/1343/reviewerName"
        },
        "reviewedAt": {
          "from": "/rows/47/reviewedAt",
          "to": "/rows/1343/reviewedAt"
        },
        "realHumanInput": {
          "from": "/rows/47/realHumanInput",
          "to": "/rows/1343/realHumanInput"
        }
      }
    },
    {
      "packetRowIndex": 48,
      "targetFullDraftRowIndex": 1410,
      "reviewId": "knv2_0323::corpus_0423",
      "nodeId": "knv2_0323",
      "documentId": "corpus_0423",
      "sourceName": "Wikipedia: Diversification (finance)",
      "mappedToFullDraft": true,
      "packetValidationStatus": "blocked_missing_or_invalid_reviewer_input",
      "readyForMerge": false,
      "mergeBlockedReason": "packet_row_not_ready_for_merge",
      "fieldCopyPlan": {
        "reviewerDecision": {
          "from": "/rows/48/reviewerDecision",
          "to": "/rows/1410/reviewerDecision"
        },
        "sourceFitNotes": {
          "from": "/rows/48/sourceFitNotes",
          "to": "/rows/1410/sourceFitNotes"
        },
        "citationUse": {
          "from": "/rows/48/citationUse",
          "to": "/rows/1410/citationUse"
        },
        "reviewerName": {
          "from": "/rows/48/reviewerName",
          "to": "/rows/1410/reviewerName"
        },
        "reviewedAt": {
          "from": "/rows/48/reviewedAt",
          "to": "/rows/1410/reviewedAt"
        },
        "realHumanInput": {
          "from": "/rows/48/realHumanInput",
          "to": "/rows/1410/realHumanInput"
        }
      }
    },
    {
      "packetRowIndex": 49,
      "targetFullDraftRowIndex": 1411,
      "reviewId": "knv2_0323::corpus_0042",
      "nodeId": "knv2_0323",
      "documentId": "corpus_0042",
      "sourceName": "CFTC Speculative Limits",
      "mappedToFullDraft": true,
      "packetValidationStatus": "blocked_missing_or_invalid_reviewer_input",
      "readyForMerge": false,
      "mergeBlockedReason": "packet_row_not_ready_for_merge",
      "fieldCopyPlan": {
        "reviewerDecision": {
          "from": "/rows/49/reviewerDecision",
          "to": "/rows/1411/reviewerDecision"
        },
        "sourceFitNotes": {
          "from": "/rows/49/sourceFitNotes",
          "to": "/rows/1411/sourceFitNotes"
        },
        "citationUse": {
          "from": "/rows/49/citationUse",
          "to": "/rows/1411/citationUse"
        },
        "reviewerName": {
          "from": "/rows/49/reviewerName",
          "to": "/rows/1411/reviewerName"
        },
        "reviewedAt": {
          "from": "/rows/49/reviewedAt",
          "to": "/rows/1411/reviewedAt"
        },
        "realHumanInput": {
          "from": "/rows/49/realHumanInput",
          "to": "/rows/1411/realHumanInput"
        }
      }
    },
    {
      "packetRowIndex": 50,
      "targetFullDraftRowIndex": 1412,
      "reviewId": "knv2_0323::corpus_0646",
      "nodeId": "knv2_0323",
      "documentId": "corpus_0646",
      "sourceName": "A note on estimating stochastic volatility and its volatility: a new simple method",
      "mappedToFullDraft": true,
      "packetValidationStatus": "blocked_missing_or_invalid_reviewer_input",
      "readyForMerge": false,
      "mergeBlockedReason": "packet_row_not_ready_for_merge",
      "fieldCopyPlan": {
        "reviewerDecision": {
          "from": "/rows/50/reviewerDecision",
          "to": "/rows/1412/reviewerDecision"
        },
        "sourceFitNotes": {
          "from": "/rows/50/sourceFitNotes",
          "to": "/rows/1412/sourceFitNotes"
        },
        "citationUse": {
          "from": "/rows/50/citationUse",
          "to": "/rows/1412/citationUse"
        },
        "reviewerName": {
          "from": "/rows/50/reviewerName",
          "to": "/rows/1412/reviewerName"
        },
        "reviewedAt": {
          "from": "/rows/50/reviewedAt",
          "to": "/rows/1412/reviewedAt"
        },
        "realHumanInput": {
          "from": "/rows/50/realHumanInput",
          "to": "/rows/1412/realHumanInput"
        }
      }
    },
    {
      "packetRowIndex": 51,
      "targetFullDraftRowIndex": 1413,
      "reviewId": "knv2_0323::corpus_0422",
      "nodeId": "knv2_0323",
      "documentId": "corpus_0422",
      "sourceName": "Wikipedia: Drawdown (economics)",
      "mappedToFullDraft": true,
      "packetValidationStatus": "blocked_missing_or_invalid_reviewer_input",
      "readyForMerge": false,
      "mergeBlockedReason": "packet_row_not_ready_for_merge",
      "fieldCopyPlan": {
        "reviewerDecision": {
          "from": "/rows/51/reviewerDecision",
          "to": "/rows/1413/reviewerDecision"
        },
        "sourceFitNotes": {
          "from": "/rows/51/sourceFitNotes",
          "to": "/rows/1413/sourceFitNotes"
        },
        "citationUse": {
          "from": "/rows/51/citationUse",
          "to": "/rows/1413/citationUse"
        },
        "reviewerName": {
          "from": "/rows/51/reviewerName",
          "to": "/rows/1413/reviewerName"
        },
        "reviewedAt": {
          "from": "/rows/51/reviewedAt",
          "to": "/rows/1413/reviewedAt"
        },
        "realHumanInput": {
          "from": "/rows/51/realHumanInput",
          "to": "/rows/1413/realHumanInput"
        }
      }
    },
    {
      "packetRowIndex": 52,
      "targetFullDraftRowIndex": 1414,
      "reviewId": "knv2_0323::corpus_0421",
      "nodeId": "knv2_0323",
      "documentId": "corpus_0421",
      "sourceName": "Wikipedia: Kelly criterion",
      "mappedToFullDraft": true,
      "packetValidationStatus": "blocked_missing_or_invalid_reviewer_input",
      "readyForMerge": false,
      "mergeBlockedReason": "packet_row_not_ready_for_merge",
      "fieldCopyPlan": {
        "reviewerDecision": {
          "from": "/rows/52/reviewerDecision",
          "to": "/rows/1414/reviewerDecision"
        },
        "sourceFitNotes": {
          "from": "/rows/52/sourceFitNotes",
          "to": "/rows/1414/sourceFitNotes"
        },
        "citationUse": {
          "from": "/rows/52/citationUse",
          "to": "/rows/1414/citationUse"
        },
        "reviewerName": {
          "from": "/rows/52/reviewerName",
          "to": "/rows/1414/reviewerName"
        },
        "reviewedAt": {
          "from": "/rows/52/reviewedAt",
          "to": "/rows/1414/reviewedAt"
        },
        "realHumanInput": {
          "from": "/rows/52/realHumanInput",
          "to": "/rows/1414/realHumanInput"
        }
      }
    },
    {
      "packetRowIndex": 53,
      "targetFullDraftRowIndex": 1415,
      "reviewId": "knv2_0323::corpus_0458",
      "nodeId": "knv2_0323",
      "documentId": "corpus_0458",
      "sourceName": "Wikipedia: Leverage (finance)",
      "mappedToFullDraft": true,
      "packetValidationStatus": "blocked_missing_or_invalid_reviewer_input",
      "readyForMerge": false,
      "mergeBlockedReason": "packet_row_not_ready_for_merge",
      "fieldCopyPlan": {
        "reviewerDecision": {
          "from": "/rows/53/reviewerDecision",
          "to": "/rows/1415/reviewerDecision"
        },
        "sourceFitNotes": {
          "from": "/rows/53/sourceFitNotes",
          "to": "/rows/1415/sourceFitNotes"
        },
        "citationUse": {
          "from": "/rows/53/citationUse",
          "to": "/rows/1415/citationUse"
        },
        "reviewerName": {
          "from": "/rows/53/reviewerName",
          "to": "/rows/1415/reviewerName"
        },
        "reviewedAt": {
          "from": "/rows/53/reviewedAt",
          "to": "/rows/1415/reviewedAt"
        },
        "realHumanInput": {
          "from": "/rows/53/realHumanInput",
          "to": "/rows/1415/realHumanInput"
        }
      }
    },
    {
      "packetRowIndex": 54,
      "targetFullDraftRowIndex": 1482,
      "reviewId": "knv2_0335::corpus_0423",
      "nodeId": "knv2_0335",
      "documentId": "corpus_0423",
      "sourceName": "Wikipedia: Diversification (finance)",
      "mappedToFullDraft": true,
      "packetValidationStatus": "blocked_missing_or_invalid_reviewer_input",
      "readyForMerge": false,
      "mergeBlockedReason": "packet_row_not_ready_for_merge",
      "fieldCopyPlan": {
        "reviewerDecision": {
          "from": "/rows/54/reviewerDecision",
          "to": "/rows/1482/reviewerDecision"
        },
        "sourceFitNotes": {
          "from": "/rows/54/sourceFitNotes",
          "to": "/rows/1482/sourceFitNotes"
        },
        "citationUse": {
          "from": "/rows/54/citationUse",
          "to": "/rows/1482/citationUse"
        },
        "reviewerName": {
          "from": "/rows/54/reviewerName",
          "to": "/rows/1482/reviewerName"
        },
        "reviewedAt": {
          "from": "/rows/54/reviewedAt",
          "to": "/rows/1482/reviewedAt"
        },
        "realHumanInput": {
          "from": "/rows/54/realHumanInput",
          "to": "/rows/1482/realHumanInput"
        }
      }
    },
    {
      "packetRowIndex": 55,
      "targetFullDraftRowIndex": 1483,
      "reviewId": "knv2_0335::corpus_0042",
      "nodeId": "knv2_0335",
      "documentId": "corpus_0042",
      "sourceName": "CFTC Speculative Limits",
      "mappedToFullDraft": true,
      "packetValidationStatus": "blocked_missing_or_invalid_reviewer_input",
      "readyForMerge": false,
      "mergeBlockedReason": "packet_row_not_ready_for_merge",
      "fieldCopyPlan": {
        "reviewerDecision": {
          "from": "/rows/55/reviewerDecision",
          "to": "/rows/1483/reviewerDecision"
        },
        "sourceFitNotes": {
          "from": "/rows/55/sourceFitNotes",
          "to": "/rows/1483/sourceFitNotes"
        },
        "citationUse": {
          "from": "/rows/55/citationUse",
          "to": "/rows/1483/citationUse"
        },
        "reviewerName": {
          "from": "/rows/55/reviewerName",
          "to": "/rows/1483/reviewerName"
        },
        "reviewedAt": {
          "from": "/rows/55/reviewedAt",
          "to": "/rows/1483/reviewedAt"
        },
        "realHumanInput": {
          "from": "/rows/55/realHumanInput",
          "to": "/rows/1483/realHumanInput"
        }
      }
    },
    {
      "packetRowIndex": 56,
      "targetFullDraftRowIndex": 1484,
      "reviewId": "knv2_0335::corpus_0646",
      "nodeId": "knv2_0335",
      "documentId": "corpus_0646",
      "sourceName": "A note on estimating stochastic volatility and its volatility: a new simple method",
      "mappedToFullDraft": true,
      "packetValidationStatus": "blocked_missing_or_invalid_reviewer_input",
      "readyForMerge": false,
      "mergeBlockedReason": "packet_row_not_ready_for_merge",
      "fieldCopyPlan": {
        "reviewerDecision": {
          "from": "/rows/56/reviewerDecision",
          "to": "/rows/1484/reviewerDecision"
        },
        "sourceFitNotes": {
          "from": "/rows/56/sourceFitNotes",
          "to": "/rows/1484/sourceFitNotes"
        },
        "citationUse": {
          "from": "/rows/56/citationUse",
          "to": "/rows/1484/citationUse"
        },
        "reviewerName": {
          "from": "/rows/56/reviewerName",
          "to": "/rows/1484/reviewerName"
        },
        "reviewedAt": {
          "from": "/rows/56/reviewedAt",
          "to": "/rows/1484/reviewedAt"
        },
        "realHumanInput": {
          "from": "/rows/56/realHumanInput",
          "to": "/rows/1484/realHumanInput"
        }
      }
    },
    {
      "packetRowIndex": 57,
      "targetFullDraftRowIndex": 1485,
      "reviewId": "knv2_0335::corpus_0422",
      "nodeId": "knv2_0335",
      "documentId": "corpus_0422",
      "sourceName": "Wikipedia: Drawdown (economics)",
      "mappedToFullDraft": true,
      "packetValidationStatus": "blocked_missing_or_invalid_reviewer_input",
      "readyForMerge": false,
      "mergeBlockedReason": "packet_row_not_ready_for_merge",
      "fieldCopyPlan": {
        "reviewerDecision": {
          "from": "/rows/57/reviewerDecision",
          "to": "/rows/1485/reviewerDecision"
        },
        "sourceFitNotes": {
          "from": "/rows/57/sourceFitNotes",
          "to": "/rows/1485/sourceFitNotes"
        },
        "citationUse": {
          "from": "/rows/57/citationUse",
          "to": "/rows/1485/citationUse"
        },
        "reviewerName": {
          "from": "/rows/57/reviewerName",
          "to": "/rows/1485/reviewerName"
        },
        "reviewedAt": {
          "from": "/rows/57/reviewedAt",
          "to": "/rows/1485/reviewedAt"
        },
        "realHumanInput": {
          "from": "/rows/57/realHumanInput",
          "to": "/rows/1485/realHumanInput"
        }
      }
    },
    {
      "packetRowIndex": 58,
      "targetFullDraftRowIndex": 1486,
      "reviewId": "knv2_0335::corpus_0421",
      "nodeId": "knv2_0335",
      "documentId": "corpus_0421",
      "sourceName": "Wikipedia: Kelly criterion",
      "mappedToFullDraft": true,
      "packetValidationStatus": "blocked_missing_or_invalid_reviewer_input",
      "readyForMerge": false,
      "mergeBlockedReason": "packet_row_not_ready_for_merge",
      "fieldCopyPlan": {
        "reviewerDecision": {
          "from": "/rows/58/reviewerDecision",
          "to": "/rows/1486/reviewerDecision"
        },
        "sourceFitNotes": {
          "from": "/rows/58/sourceFitNotes",
          "to": "/rows/1486/sourceFitNotes"
        },
        "citationUse": {
          "from": "/rows/58/citationUse",
          "to": "/rows/1486/citationUse"
        },
        "reviewerName": {
          "from": "/rows/58/reviewerName",
          "to": "/rows/1486/reviewerName"
        },
        "reviewedAt": {
          "from": "/rows/58/reviewedAt",
          "to": "/rows/1486/reviewedAt"
        },
        "realHumanInput": {
          "from": "/rows/58/realHumanInput",
          "to": "/rows/1486/realHumanInput"
        }
      }
    },
    {
      "packetRowIndex": 59,
      "targetFullDraftRowIndex": 1487,
      "reviewId": "knv2_0335::corpus_0458",
      "nodeId": "knv2_0335",
      "documentId": "corpus_0458",
      "sourceName": "Wikipedia: Leverage (finance)",
      "mappedToFullDraft": true,
      "packetValidationStatus": "blocked_missing_or_invalid_reviewer_input",
      "readyForMerge": false,
      "mergeBlockedReason": "packet_row_not_ready_for_merge",
      "fieldCopyPlan": {
        "reviewerDecision": {
          "from": "/rows/59/reviewerDecision",
          "to": "/rows/1487/reviewerDecision"
        },
        "sourceFitNotes": {
          "from": "/rows/59/sourceFitNotes",
          "to": "/rows/1487/sourceFitNotes"
        },
        "citationUse": {
          "from": "/rows/59/citationUse",
          "to": "/rows/1487/citationUse"
        },
        "reviewerName": {
          "from": "/rows/59/reviewerName",
          "to": "/rows/1487/reviewerName"
        },
        "reviewedAt": {
          "from": "/rows/59/reviewedAt",
          "to": "/rows/1487/reviewedAt"
        },
        "realHumanInput": {
          "from": "/rows/59/realHumanInput",
          "to": "/rows/1487/realHumanInput"
        }
      }
    }
  ],
  "sampleMergeRows": [
    {
      "packetRowIndex": 0,
      "targetFullDraftRowIndex": 846,
      "reviewId": "knv2_0227::corpus_0423",
      "nodeId": "knv2_0227",
      "documentId": "corpus_0423",
      "sourceName": "Wikipedia: Diversification (finance)",
      "mappedToFullDraft": true,
      "packetValidationStatus": "blocked_missing_or_invalid_reviewer_input",
      "readyForMerge": false,
      "mergeBlockedReason": "packet_row_not_ready_for_merge",
      "fieldCopyPlan": {
        "reviewerDecision": {
          "from": "/rows/0/reviewerDecision",
          "to": "/rows/846/reviewerDecision"
        },
        "sourceFitNotes": {
          "from": "/rows/0/sourceFitNotes",
          "to": "/rows/846/sourceFitNotes"
        },
        "citationUse": {
          "from": "/rows/0/citationUse",
          "to": "/rows/846/citationUse"
        },
        "reviewerName": {
          "from": "/rows/0/reviewerName",
          "to": "/rows/846/reviewerName"
        },
        "reviewedAt": {
          "from": "/rows/0/reviewedAt",
          "to": "/rows/846/reviewedAt"
        },
        "realHumanInput": {
          "from": "/rows/0/realHumanInput",
          "to": "/rows/846/realHumanInput"
        }
      }
    },
    {
      "packetRowIndex": 1,
      "targetFullDraftRowIndex": 847,
      "reviewId": "knv2_0227::corpus_0042",
      "nodeId": "knv2_0227",
      "documentId": "corpus_0042",
      "sourceName": "CFTC Speculative Limits",
      "mappedToFullDraft": true,
      "packetValidationStatus": "blocked_missing_or_invalid_reviewer_input",
      "readyForMerge": false,
      "mergeBlockedReason": "packet_row_not_ready_for_merge",
      "fieldCopyPlan": {
        "reviewerDecision": {
          "from": "/rows/1/reviewerDecision",
          "to": "/rows/847/reviewerDecision"
        },
        "sourceFitNotes": {
          "from": "/rows/1/sourceFitNotes",
          "to": "/rows/847/sourceFitNotes"
        },
        "citationUse": {
          "from": "/rows/1/citationUse",
          "to": "/rows/847/citationUse"
        },
        "reviewerName": {
          "from": "/rows/1/reviewerName",
          "to": "/rows/847/reviewerName"
        },
        "reviewedAt": {
          "from": "/rows/1/reviewedAt",
          "to": "/rows/847/reviewedAt"
        },
        "realHumanInput": {
          "from": "/rows/1/realHumanInput",
          "to": "/rows/847/realHumanInput"
        }
      }
    },
    {
      "packetRowIndex": 2,
      "targetFullDraftRowIndex": 848,
      "reviewId": "knv2_0227::corpus_0646",
      "nodeId": "knv2_0227",
      "documentId": "corpus_0646",
      "sourceName": "A note on estimating stochastic volatility and its volatility: a new simple method",
      "mappedToFullDraft": true,
      "packetValidationStatus": "blocked_missing_or_invalid_reviewer_input",
      "readyForMerge": false,
      "mergeBlockedReason": "packet_row_not_ready_for_merge",
      "fieldCopyPlan": {
        "reviewerDecision": {
          "from": "/rows/2/reviewerDecision",
          "to": "/rows/848/reviewerDecision"
        },
        "sourceFitNotes": {
          "from": "/rows/2/sourceFitNotes",
          "to": "/rows/848/sourceFitNotes"
        },
        "citationUse": {
          "from": "/rows/2/citationUse",
          "to": "/rows/848/citationUse"
        },
        "reviewerName": {
          "from": "/rows/2/reviewerName",
          "to": "/rows/848/reviewerName"
        },
        "reviewedAt": {
          "from": "/rows/2/reviewedAt",
          "to": "/rows/848/reviewedAt"
        },
        "realHumanInput": {
          "from": "/rows/2/realHumanInput",
          "to": "/rows/848/realHumanInput"
        }
      }
    },
    {
      "packetRowIndex": 3,
      "targetFullDraftRowIndex": 849,
      "reviewId": "knv2_0227::corpus_0422",
      "nodeId": "knv2_0227",
      "documentId": "corpus_0422",
      "sourceName": "Wikipedia: Drawdown (economics)",
      "mappedToFullDraft": true,
      "packetValidationStatus": "blocked_missing_or_invalid_reviewer_input",
      "readyForMerge": false,
      "mergeBlockedReason": "packet_row_not_ready_for_merge",
      "fieldCopyPlan": {
        "reviewerDecision": {
          "from": "/rows/3/reviewerDecision",
          "to": "/rows/849/reviewerDecision"
        },
        "sourceFitNotes": {
          "from": "/rows/3/sourceFitNotes",
          "to": "/rows/849/sourceFitNotes"
        },
        "citationUse": {
          "from": "/rows/3/citationUse",
          "to": "/rows/849/citationUse"
        },
        "reviewerName": {
          "from": "/rows/3/reviewerName",
          "to": "/rows/849/reviewerName"
        },
        "reviewedAt": {
          "from": "/rows/3/reviewedAt",
          "to": "/rows/849/reviewedAt"
        },
        "realHumanInput": {
          "from": "/rows/3/realHumanInput",
          "to": "/rows/849/realHumanInput"
        }
      }
    },
    {
      "packetRowIndex": 4,
      "targetFullDraftRowIndex": 850,
      "reviewId": "knv2_0227::corpus_0421",
      "nodeId": "knv2_0227",
      "documentId": "corpus_0421",
      "sourceName": "Wikipedia: Kelly criterion",
      "mappedToFullDraft": true,
      "packetValidationStatus": "blocked_missing_or_invalid_reviewer_input",
      "readyForMerge": false,
      "mergeBlockedReason": "packet_row_not_ready_for_merge",
      "fieldCopyPlan": {
        "reviewerDecision": {
          "from": "/rows/4/reviewerDecision",
          "to": "/rows/850/reviewerDecision"
        },
        "sourceFitNotes": {
          "from": "/rows/4/sourceFitNotes",
          "to": "/rows/850/sourceFitNotes"
        },
        "citationUse": {
          "from": "/rows/4/citationUse",
          "to": "/rows/850/citationUse"
        },
        "reviewerName": {
          "from": "/rows/4/reviewerName",
          "to": "/rows/850/reviewerName"
        },
        "reviewedAt": {
          "from": "/rows/4/reviewedAt",
          "to": "/rows/850/reviewedAt"
        },
        "realHumanInput": {
          "from": "/rows/4/realHumanInput",
          "to": "/rows/850/realHumanInput"
        }
      }
    },
    {
      "packetRowIndex": 5,
      "targetFullDraftRowIndex": 851,
      "reviewId": "knv2_0227::corpus_0458",
      "nodeId": "knv2_0227",
      "documentId": "corpus_0458",
      "sourceName": "Wikipedia: Leverage (finance)",
      "mappedToFullDraft": true,
      "packetValidationStatus": "blocked_missing_or_invalid_reviewer_input",
      "readyForMerge": false,
      "mergeBlockedReason": "packet_row_not_ready_for_merge",
      "fieldCopyPlan": {
        "reviewerDecision": {
          "from": "/rows/5/reviewerDecision",
          "to": "/rows/851/reviewerDecision"
        },
        "sourceFitNotes": {
          "from": "/rows/5/sourceFitNotes",
          "to": "/rows/851/sourceFitNotes"
        },
        "citationUse": {
          "from": "/rows/5/citationUse",
          "to": "/rows/851/citationUse"
        },
        "reviewerName": {
          "from": "/rows/5/reviewerName",
          "to": "/rows/851/reviewerName"
        },
        "reviewedAt": {
          "from": "/rows/5/reviewedAt",
          "to": "/rows/851/reviewedAt"
        },
        "realHumanInput": {
          "from": "/rows/5/realHumanInput",
          "to": "/rows/851/realHumanInput"
        }
      }
    },
    {
      "packetRowIndex": 6,
      "targetFullDraftRowIndex": 918,
      "reviewId": "knv2_0239::corpus_0423",
      "nodeId": "knv2_0239",
      "documentId": "corpus_0423",
      "sourceName": "Wikipedia: Diversification (finance)",
      "mappedToFullDraft": true,
      "packetValidationStatus": "blocked_missing_or_invalid_reviewer_input",
      "readyForMerge": false,
      "mergeBlockedReason": "packet_row_not_ready_for_merge",
      "fieldCopyPlan": {
        "reviewerDecision": {
          "from": "/rows/6/reviewerDecision",
          "to": "/rows/918/reviewerDecision"
        },
        "sourceFitNotes": {
          "from": "/rows/6/sourceFitNotes",
          "to": "/rows/918/sourceFitNotes"
        },
        "citationUse": {
          "from": "/rows/6/citationUse",
          "to": "/rows/918/citationUse"
        },
        "reviewerName": {
          "from": "/rows/6/reviewerName",
          "to": "/rows/918/reviewerName"
        },
        "reviewedAt": {
          "from": "/rows/6/reviewedAt",
          "to": "/rows/918/reviewedAt"
        },
        "realHumanInput": {
          "from": "/rows/6/realHumanInput",
          "to": "/rows/918/realHumanInput"
        }
      }
    },
    {
      "packetRowIndex": 7,
      "targetFullDraftRowIndex": 919,
      "reviewId": "knv2_0239::corpus_0042",
      "nodeId": "knv2_0239",
      "documentId": "corpus_0042",
      "sourceName": "CFTC Speculative Limits",
      "mappedToFullDraft": true,
      "packetValidationStatus": "blocked_missing_or_invalid_reviewer_input",
      "readyForMerge": false,
      "mergeBlockedReason": "packet_row_not_ready_for_merge",
      "fieldCopyPlan": {
        "reviewerDecision": {
          "from": "/rows/7/reviewerDecision",
          "to": "/rows/919/reviewerDecision"
        },
        "sourceFitNotes": {
          "from": "/rows/7/sourceFitNotes",
          "to": "/rows/919/sourceFitNotes"
        },
        "citationUse": {
          "from": "/rows/7/citationUse",
          "to": "/rows/919/citationUse"
        },
        "reviewerName": {
          "from": "/rows/7/reviewerName",
          "to": "/rows/919/reviewerName"
        },
        "reviewedAt": {
          "from": "/rows/7/reviewedAt",
          "to": "/rows/919/reviewedAt"
        },
        "realHumanInput": {
          "from": "/rows/7/realHumanInput",
          "to": "/rows/919/realHumanInput"
        }
      }
    },
    {
      "packetRowIndex": 8,
      "targetFullDraftRowIndex": 920,
      "reviewId": "knv2_0239::corpus_0646",
      "nodeId": "knv2_0239",
      "documentId": "corpus_0646",
      "sourceName": "A note on estimating stochastic volatility and its volatility: a new simple method",
      "mappedToFullDraft": true,
      "packetValidationStatus": "blocked_missing_or_invalid_reviewer_input",
      "readyForMerge": false,
      "mergeBlockedReason": "packet_row_not_ready_for_merge",
      "fieldCopyPlan": {
        "reviewerDecision": {
          "from": "/rows/8/reviewerDecision",
          "to": "/rows/920/reviewerDecision"
        },
        "sourceFitNotes": {
          "from": "/rows/8/sourceFitNotes",
          "to": "/rows/920/sourceFitNotes"
        },
        "citationUse": {
          "from": "/rows/8/citationUse",
          "to": "/rows/920/citationUse"
        },
        "reviewerName": {
          "from": "/rows/8/reviewerName",
          "to": "/rows/920/reviewerName"
        },
        "reviewedAt": {
          "from": "/rows/8/reviewedAt",
          "to": "/rows/920/reviewedAt"
        },
        "realHumanInput": {
          "from": "/rows/8/realHumanInput",
          "to": "/rows/920/realHumanInput"
        }
      }
    },
    {
      "packetRowIndex": 9,
      "targetFullDraftRowIndex": 921,
      "reviewId": "knv2_0239::corpus_0422",
      "nodeId": "knv2_0239",
      "documentId": "corpus_0422",
      "sourceName": "Wikipedia: Drawdown (economics)",
      "mappedToFullDraft": true,
      "packetValidationStatus": "blocked_missing_or_invalid_reviewer_input",
      "readyForMerge": false,
      "mergeBlockedReason": "packet_row_not_ready_for_merge",
      "fieldCopyPlan": {
        "reviewerDecision": {
          "from": "/rows/9/reviewerDecision",
          "to": "/rows/921/reviewerDecision"
        },
        "sourceFitNotes": {
          "from": "/rows/9/sourceFitNotes",
          "to": "/rows/921/sourceFitNotes"
        },
        "citationUse": {
          "from": "/rows/9/citationUse",
          "to": "/rows/921/citationUse"
        },
        "reviewerName": {
          "from": "/rows/9/reviewerName",
          "to": "/rows/921/reviewerName"
        },
        "reviewedAt": {
          "from": "/rows/9/reviewedAt",
          "to": "/rows/921/reviewedAt"
        },
        "realHumanInput": {
          "from": "/rows/9/realHumanInput",
          "to": "/rows/921/realHumanInput"
        }
      }
    },
    {
      "packetRowIndex": 10,
      "targetFullDraftRowIndex": 922,
      "reviewId": "knv2_0239::corpus_0421",
      "nodeId": "knv2_0239",
      "documentId": "corpus_0421",
      "sourceName": "Wikipedia: Kelly criterion",
      "mappedToFullDraft": true,
      "packetValidationStatus": "blocked_missing_or_invalid_reviewer_input",
      "readyForMerge": false,
      "mergeBlockedReason": "packet_row_not_ready_for_merge",
      "fieldCopyPlan": {
        "reviewerDecision": {
          "from": "/rows/10/reviewerDecision",
          "to": "/rows/922/reviewerDecision"
        },
        "sourceFitNotes": {
          "from": "/rows/10/sourceFitNotes",
          "to": "/rows/922/sourceFitNotes"
        },
        "citationUse": {
          "from": "/rows/10/citationUse",
          "to": "/rows/922/citationUse"
        },
        "reviewerName": {
          "from": "/rows/10/reviewerName",
          "to": "/rows/922/reviewerName"
        },
        "reviewedAt": {
          "from": "/rows/10/reviewedAt",
          "to": "/rows/922/reviewedAt"
        },
        "realHumanInput": {
          "from": "/rows/10/realHumanInput",
          "to": "/rows/922/realHumanInput"
        }
      }
    },
    {
      "packetRowIndex": 11,
      "targetFullDraftRowIndex": 923,
      "reviewId": "knv2_0239::corpus_0458",
      "nodeId": "knv2_0239",
      "documentId": "corpus_0458",
      "sourceName": "Wikipedia: Leverage (finance)",
      "mappedToFullDraft": true,
      "packetValidationStatus": "blocked_missing_or_invalid_reviewer_input",
      "readyForMerge": false,
      "mergeBlockedReason": "packet_row_not_ready_for_merge",
      "fieldCopyPlan": {
        "reviewerDecision": {
          "from": "/rows/11/reviewerDecision",
          "to": "/rows/923/reviewerDecision"
        },
        "sourceFitNotes": {
          "from": "/rows/11/sourceFitNotes",
          "to": "/rows/923/sourceFitNotes"
        },
        "citationUse": {
          "from": "/rows/11/citationUse",
          "to": "/rows/923/citationUse"
        },
        "reviewerName": {
          "from": "/rows/11/reviewerName",
          "to": "/rows/923/reviewerName"
        },
        "reviewedAt": {
          "from": "/rows/11/reviewedAt",
          "to": "/rows/923/reviewedAt"
        },
        "realHumanInput": {
          "from": "/rows/11/realHumanInput",
          "to": "/rows/923/realHumanInput"
        }
      }
    }
  ],
  "commands": [
    "npm.cmd run build:knowledge-node-public-source-fit-review-packet-014-suite",
    "npm.cmd run check:knowledge-node-public-source-fit-review-packet-014-suite"
  ],
  "completionRule": "Packet 014 merge preview becomes ready only when the packet input copy validates every row as real human input, every packet row maps to the full 1638-row draft, forbidden hits are zero, learnerCitationApproved:false, copiedTextApproved:false, and a separate manual merge/write authorization exists.",
  "boundary": "Packet 014 merge preview is dry-run reviewer operations only. It does not write the full source-fit draft, create human judgments, approve copied text, approve learner-facing citations, write lessons, provide stock recommendations, live signals, return promises, broker workflows, automation, real-money guidance, or production readiness."
}
